mitea_hires/__init__.py
mitea_hires/constants.py
mitea_hires/main.py
mitea_hires/utils.py
mitea_hires/miRTarBase/hsa_MTI.csv
mitea_hires/miRTarBase/hsa_MTI_filtered.csv
mitea_hires/miRTarBase/mmu_MTI.csv
mitea_hires/miRTarBase/mmu_MTI_filtered.csv
mitea_hires-0.0.19.dist-info/LICENSE
mitea_hires-0.0.19.dist-info/METADATA
mitea_hires-0.0.19.dist-info/WHEEL
mitea_hires-0.0.19.dist-info/entry_points.txt
mitea_hires-0.0.19.dist-info/top_level.txt
mitea_hires-0.0.19.dist-info/RECORD
