Metadata-Version: 2.1
Name: mitea_hires
Version: 0.0.19
Summary: Infer single-cell and spatial microRNA activity from transcriptomics data
Author-email: Efrat Herbst <efiherbst@gmail.com>
Project-URL: Repository, https://github.com/EfiHerbst31/miTEA-HiRes
Project-URL: Issues, https://github.com/EfiHerbst31/miTEA-HiRes/issues
Keywords: microrna,mir,mitea,single-cell,spatial,gene expression,rna sequencing
Classifier: Programming Language :: Python :: 3
Classifier: License :: OSI Approved :: MIT License
Classifier: Operating System :: OS Independent
Requires-Python: >=3.8
License-File: LICENSE
Requires-Dist: absl-py
Requires-Dist: anndata
Requires-Dist: matplotlib
Requires-Dist: numpy ==1.23
Requires-Dist: pandas ==1.5.2
Requires-Dist: scanpy
Requires-Dist: scipy
Requires-Dist: tqdm ==4.64.1
Requires-Dist: xlmhg
